[["int",{"count":1888,"selection":true}],["us",{"count":280,"selection":true}],["gb",{"count":99,"selection":true}],["de",{"count":85,"selection":true}],["ca",{"count":64,"selection":true}],["au",{"count":52,"selection":true}],["fr",{"count":40,"selection":true}],["se",{"count":37,"selection":true}],["ar",{"count":31,"selection":true}],["it",{"count":30,"selection":true}],["nl",{"count":29,"selection":true}],["ch",{"count":25,"selection":true}],["es",{"count":21,"selection":true}],["ie",{"count":19,"selection":true}],["mx",{"count":18,"selection":true}],["dk",{"count":16,"selection":true}],["pl",{"count":16,"selection":true}],["br",{"count":16,"selection":true}],["in",{"count":16,"selection":true}],["jp",{"count":15,"selection":true}],["no",{"count":15,"selection":true}],["nz",{"count":14,"selection":true}],["fi",{"count":13,"selection":true}],["at",{"count":13,"selection":true}],["cz",{"count":13,"selection":true}],["hr",{"count":13,"selection":true}],["be",{"count":13,"selection":true}],["pt",{"count":12,"selection":true}],["sg",{"count":12,"selection":true}],["cl",{"count":9,"selection":false}],["il",{"count":8,"selection":false}],["kr",{"count":8,"selection":false}],["pe",{"count":8,"selection":false}],["cn",{"count":7,"selection":false}],["co",{"count":7,"selection":false}],["ro",{"count":6,"selection":false}],["sv",{"count":6,"selection":false}],["lu",{"count":6,"selection":false}],["za",{"count":6,"selection":false}],["gr",{"count":6,"selection":false}],["gt",{"count":6,"selection":false}],["si",{"count":6,"selection":false}],["tw",{"count":6,"selection":false}],["hk",{"count":6,"selection":false}],["sk",{"count":6,"selection":false}],["hu",{"count":6,"selection":false}],["cr",{"count":6,"selection":false}],["th",{"count":5,"selection":false}],["id",{"count":5,"selection":false}],["ru",{"count":5,"selection":false}],["hn",{"count":5,"selection":false}],["pa",{"count":4,"selection":false}],["ee",{"count":4,"selection":false}],["ni",{"count":4,"selection":false}],["ph",{"count":4,"selection":false}],["do",{"count":4,"selection":false}],["bg",{"count":4,"selection":false}],["ec",{"count":4,"selection":false}],["is",{"count":4,"selection":false}],["lv",{"count":3,"selection":false}],["uy",{"count":3,"selection":false}],["my",{"count":3,"selection":false}],["ae",{"count":3,"selection":false}],["cy",{"count":3,"selection":false}],["lt",{"count":3,"selection":false}],["mt",{"count":3,"selection":false}],["py",{"count":3,"selection":false}],["kw",{"count":3,"selection":false}],["li",{"count":3,"selection":false}],["pr",{"count":3,"selection":false}],["aw",{"count":2,"selection":false}],["lk",{"count":2,"selection":false}],["ge",{"count":2,"selection":false}],["tt",{"count":2,"selection":false}],["qa",{"count":2,"selection":false}],["tr",{"count":2,"selection":false}],["ve",{"count":2,"selection":false}],["bo",{"count":2,"selection":false}],["bq",{"count":1,"selection":false}],["re",{"count":1,"selection":false}],["yt",{"count":1,"selection":false}],["bd",{"count":1,"selection":false}],["ua",{"count":1,"selection":false}],["ng",{"count":1,"selection":false}],["gl",{"count":1,"selection":false}],["gf",{"count":1,"selection":false}],["bh",{"count":1,"selection":false}],["om",{"count":1,"selection":false}],["sa",{"count":1,"selection":false}],["im",{"count":1,"selection":false}],["ag",{"count":1,"selection":false}],["az",{"count":1,"selection":false}],["mg",{"count":1,"selection":false}],["bs",{"count":1,"selection":false}],["tc",{"count":1,"selection":false}],["mu",{"count":1,"selection":false}],["ky",{"count":1,"selection":false}],["cw",{"count":1,"selection":false}],["dm",{"count":1,"selection":false}],["gd",{"count":1,"selection":false}],["ms",{"count":1,"selection":false}],["kn",{"count":1,"selection":false}],["lc",{"count":1,"selection":false}],["sx",{"count":1,"selection":false}],["vc",{"count":1,"selection":false}],["nc",{"count":1,"selection":false}],["wf",{"count":1,"selection":false}],["gu",{"count":1,"selection":false}],["mc",{"count":1,"selection":false}],["bw",{"count":1,"selection":false}],["ke",{"count":1,"selection":false}],["mw",{"count":1,"selection":false}],["na",{"count":1,"selection":false}],["rw",{"count":1,"selection":false}],["tz",{"count":1,"selection":false}],["kz",{"count":1,"selection":false}],["ug",{"count":1,"selection":false}],["zm",{"count":1,"selection":false}],["rs",{"count":1,"selection":false}],["zw",{"count":1,"selection":false}]]